[
    {
        "product_id": "78545019",
        "code": "ก997"
    },
    {
        "product_id": "78544986",
        "code": "ก995"
    },
    {
        "product_id": "78544979",
        "code": "ก994"
    },
    {
        "product_id": "78544788",
        "code": "ก992"
    },
    {
        "product_id": "78544749",
        "code": "ก991"
    },
    {
        "product_id": "78544530",
        "code": "ก990"
    },
    {
        "product_id": "78590722",
        "code": "ก956"
    },
    {
        "product_id": "78590730",
        "code": "ก955"
    },
    {
        "product_id": "78590701",
        "code": "ก954"
    },
    {
        "product_id": "78590484",
        "code": "ก953"
    },
    {
        "product_id": "78590272",
        "code": "ก952"
    },
    {
        "product_id": "78590030",
        "code": "ก951"
    },
    {
        "product_id": "78590000",
        "code": "ก950"
    },
    {
        "product_id": "78589948",
        "code": "ก949"
    },
    {
        "product_id": "78590023",
        "code": "ก948"
    },
    {
        "product_id": "78589788",
        "code": "ก947"
    },
    {
        "product_id": "78589376",
        "code": "ก946"
    },
    {
        "product_id": "78589312",
        "code": "ก945"
    },
    {
        "product_id": "78589196",
        "code": "ก943"
    },
    {
        "product_id": "78588367",
        "code": "ก942"
    },
    {
        "product_id": "78588364",
        "code": "ก941"
    },
    {
        "product_id": "78588363",
        "code": "ก940"
    },
    {
        "product_id": "78588362",
        "code": "ก939"
    },
    {
        "product_id": "78588361",
        "code": "ก938"
    },
    {
        "product_id": "78588360",
        "code": "ก933"
    },
    {
        "product_id": "78584746",
        "code": "ก932"
    },
    {
        "product_id": "78584579",
        "code": "ก931"
    },
    {
        "product_id": "78583912",
        "code": "ก930"
    },
    {
        "product_id": "78583893",
        "code": "ก928"
    },
    {
        "product_id": "78583889",
        "code": "ก927"
    },
    {
        "product_id": "78583882",
        "code": "ก926"
    },
    {
        "product_id": "78583871",
        "code": "ก925"
    },
    {
        "product_id": "78583761",
        "code": "ก924"
    },
    {
        "product_id": "78583758",
        "code": "ก923"
    },
    {
        "product_id": "78583755",
        "code": "ก922"
    },
    {
        "product_id": "78583583",
        "code": "ก920"
    },
    {
        "product_id": "78583569",
        "code": "ก919"
    },
    {
        "product_id": "78583558",
        "code": "ก918"
    },
    {
        "product_id": "78583419",
        "code": "ก917"
    },
    {
        "product_id": "78583380",
        "code": "ก916"
    },
    {
        "product_id": "78581704",
        "code": "ก915"
    },
    {
        "product_id": "78581672",
        "code": "ก914"
    },
    {
        "product_id": "78558289",
        "code": "ก913"
    },
    {
        "product_id": "78556738",
        "code": "ก912"
    },
    {
        "product_id": "78546731",
        "code": "ก911"
    },
    {
        "product_id": "78546723",
        "code": "ก910"
    },
    {
        "product_id": "78546718",
        "code": "ก909"
    },
    {
        "product_id": "78546702",
        "code": "ก908"
    },
    {
        "product_id": "78546712",
        "code": "ก907"
    },
    {
        "product_id": "78546690",
        "code": "ก906"
    },
    {
        "product_id": "78546689",
        "code": "ก904"
    },
    {
        "product_id": "78546632",
        "code": "ก903"
    },
    {
        "product_id": "78546626",
        "code": "ก902"
    },
    {
        "product_id": "78546623",
        "code": "ก901"
    },
    {
        "product_id": "78546563",
        "code": "ก900"
    },
    {
        "product_id": "78546345",
        "code": "ก898"
    },
    {
        "product_id": "78546332",
        "code": "ก897"
    },
    {
        "product_id": "78546320",
        "code": "ก896"
    },
    {
        "product_id": "78546129",
        "code": "ก895"
    },
    {
        "product_id": "78546125",
        "code": "ก894"
    },
    {
        "product_id": "78546114",
        "code": "ก893"
    },
    {
        "product_id": "78546108",
        "code": "ก892"
    },
    {
        "product_id": "78546096",
        "code": "ก891"
    },
    {
        "product_id": "78546050",
        "code": "ก890"
    },
    {
        "product_id": "78546120",
        "code": "ก889"
    },
    {
        "product_id": "78546044",
        "code": "ก888"
    },
    {
        "product_id": "78546038",
        "code": "ก886"
    },
    {
        "product_id": "78546031",
        "code": "ก885"
    },
    {
        "product_id": "78546024",
        "code": "ก884"
    },
    {
        "product_id": "78546016",
        "code": "ก883"
    },
    {
        "product_id": "78546004",
        "code": "ก882"
    },
    {
        "product_id": "78546012",
        "code": "ก880"
    },
    {
        "product_id": "78545490",
        "code": "ก879"
    },
    {
        "product_id": "78545484",
        "code": "ก878"
    },
    {
        "product_id": "78545417",
        "code": "ก877"
    },
    {
        "product_id": "78545368",
        "code": "ก876"
    },
    {
        "product_id": "78545351",
        "code": "ก875"
    },
    {
        "product_id": "78545297",
        "code": "ก873"
    },
    {
        "product_id": "78545313",
        "code": "ก872"
    },
    {
        "product_id": "78545298",
        "code": "ก871"
    },
    {
        "product_id": "78545331",
        "code": "ก870"
    },
    {
        "product_id": "78545378",
        "code": "ก869"
    },
    {
        "product_id": "78545270",
        "code": "ก868"
    },
    {
        "product_id": "78545387",
        "code": "ก867"
    },
    {
        "product_id": "78545248",
        "code": "ก866"
    },
    {
        "product_id": "78545255",
        "code": "ก865"
    },
    {
        "product_id": "78543762",
        "code": "ก864"
    },
    {
        "product_id": "78542909",
        "code": "ก863"
    },
    {
        "product_id": "78541729",
        "code": "ก862"
    },
    {
        "product_id": "78541617",
        "code": "ก861"
    },
    {
        "product_id": "78541613",
        "code": "ก860"
    },
    {
        "product_id": "78541611",
        "code": "ก859"
    },
    {
        "product_id": "78540951",
        "code": "ก858"
    },
    {
        "product_id": "78540496",
        "code": "ก857"
    },
    {
        "product_id": "78540321",
        "code": "ก856"
    },
    {
        "product_id": "78540133",
        "code": "ก855"
    },
    {
        "product_id": "78540132",
        "code": "ก854"
    },
    {
        "product_id": "78540130",
        "code": "ก853"
    },
    {
        "product_id": "78540129",
        "code": "ก852"
    },
    {
        "product_id": "78540128",
        "code": "ก851"
    },
    {
        "product_id": "78540126",
        "code": "ก850"
    },
    {
        "product_id": "76578368",
        "code": "ก847"
    },
    {
        "product_id": "76579304",
        "code": "ก845"
    },
    {
        "product_id": "76579306",
        "code": "ก844"
    },
    {
        "product_id": "76578770",
        "code": "ก843"
    },
    {
        "product_id": "76578769",
        "code": "ก842"
    },
    {
        "product_id": "76578758",
        "code": "ก841"
    },
    {
        "product_id": "76578763",
        "code": "ก840"
    },
    {
        "product_id": "76578755",
        "code": "ก839"
    },
    {
        "product_id": "76579286",
        "code": "ก838"
    },
    {
        "product_id": "76578750",
        "code": "ก837"
    },
    {
        "product_id": "76578693",
        "code": "ก836"
    },
    {
        "product_id": "76578689",
        "code": "ก835"
    },
    {
        "product_id": "76578685",
        "code": "ก834"
    },
    {
        "product_id": "76578574",
        "code": "ก833"
    },
    {
        "product_id": "76578398",
        "code": "ก832"
    },
    {
        "product_id": "76579605",
        "code": "ก802"
    },
    {
        "product_id": "76579563",
        "code": "ก801"
    },
    {
        "product_id": "76579555",
        "code": "ก800"
    },
    {
        "product_id": "78592540",
        "code": "ก743"
    },
    {
        "product_id": "78592446",
        "code": "ก742"
    },
    {
        "product_id": "78592450",
        "code": "ก741"
    },
    {
        "product_id": "78592277",
        "code": "ก740"
    },
    {
        "product_id": "78592228",
        "code": "ก739"
    },
    {
        "product_id": "78592216",
        "code": "ก738"
    },
    {
        "product_id": "78592209",
        "code": "ก737"
    },
    {
        "product_id": "78592198",
        "code": "ก736"
    },
    {
        "product_id": "78592192",
        "code": "ก734"
    },
    {
        "product_id": "78592175",
        "code": "ก733"
    },
    {
        "product_id": "78592187",
        "code": "ก732"
    },
    {
        "product_id": "78592181",
        "code": "ก731"
    },
    {
        "product_id": "78592169",
        "code": "ก730"
    },
    {
        "product_id": "78592156",
        "code": "ก729"
    },
    {
        "product_id": "78592165",
        "code": "ก728"
    },
    {
        "product_id": "78592141",
        "code": "ก727"
    },
    {
        "product_id": "78592134",
        "code": "ก726"
    },
    {
        "product_id": "78592132",
        "code": "ก725"
    },
    {
        "product_id": "78592128",
        "code": "ก724"
    },
    {
        "product_id": "78592118",
        "code": "ก723"
    },
    {
        "product_id": "78592082",
        "code": "ก722"
    },
    {
        "product_id": "78592072",
        "code": "ก721"
    },
    {
        "product_id": "78591697",
        "code": "ก720"
    },
    {
        "product_id": "78591279",
        "code": "ก718"
    },
    {
        "product_id": "78591237",
        "code": "ก717"
    },
    {
        "product_id": "78591111",
        "code": "ก716"
    },
    {
        "product_id": "78591068",
        "code": "ก715"
    },
    {
        "product_id": "78591041",
        "code": "ก714"
    },
    {
        "product_id": "78591024",
        "code": "ก713"
    },
    {
        "product_id": "78590977",
        "code": "ก712"
    },
    {
        "product_id": "78590961",
        "code": "ก711"
    },
    {
        "product_id": "78590927",
        "code": "ก710"
    },
    {
        "product_id": "78590834",
        "code": "ก704"
    },
    {
        "product_id": "78590832",
        "code": "ก703"
    },
    {
        "product_id": "78590819",
        "code": "ก702"
    },
    {
        "product_id": "78590809",
        "code": "ก701"
    },
    {
        "product_id": "78590805",
        "code": "ก700"
    },
    {
        "product_id": "77830321",
        "code": "ก601"
    },
    {
        "product_id": "77830317",
        "code": "ก600"
    },
    {
        "product_id": "77830274",
        "code": "ก582"
    },
    {
        "product_id": "77830278",
        "code": "ก581"
    },
    {
        "product_id": "77830266",
        "code": "ก580"
    },
    {
        "product_id": "77830270",
        "code": "ก579"
    },
    {
        "product_id": "77830275",
        "code": "ก577"
    },
    {
        "product_id": "77830276",
        "code": "ก576"
    },
    {
        "product_id": "77830261",
        "code": "ก575"
    },
    {
        "product_id": "77830255",
        "code": "ก574"
    },
    {
        "product_id": "77830252",
        "code": "ก573"
    },
    {
        "product_id": "77830265",
        "code": "ก572"
    },
    {
        "product_id": "77861028",
        "code": "ก571"
    },
    {
        "product_id": "77830237",
        "code": "ก570"
    },
    {
        "product_id": "77861027",
        "code": "ก570"
    },
    {
        "product_id": "77830246",
        "code": "ก569"
    },
    {
        "product_id": "77861025",
        "code": "ก569"
    },
    {
        "product_id": "77830267",
        "code": "ก568"
    },
    {
        "product_id": "77861023",
        "code": "ก568"
    },
    {
        "product_id": "77861020",
        "code": "ก567"
    },
    {
        "product_id": "77830249",
        "code": "ก566"
    },
    {
        "product_id": "77861013",
        "code": "ก566"
    },
    {
        "product_id": "77861007",
        "code": "ก565"
    },
    {
        "product_id": "77830239",
        "code": "ก564"
    },
    {
        "product_id": "77861002",
        "code": "ก564"
    },
    {
        "product_id": "77830233",
        "code": "ก563"
    },
    {
        "product_id": "77860998",
        "code": "ก563"
    },
    {
        "product_id": "77860992",
        "code": "ก562"
    },
    {
        "product_id": "77830221",
        "code": "ก561"
    },
    {
        "product_id": "77860986",
        "code": "ก561"
    },
    {
        "product_id": "77830220",
        "code": "ก560"
    },
    {
        "product_id": "77860983",
        "code": "ก560"
    },
    {
        "product_id": "77830219",
        "code": "ก559"
    },
    {
        "product_id": "77860877",
        "code": "ก559"
    },
    {
        "product_id": "77830218",
        "code": "ก558"
    },
    {
        "product_id": "77860979",
        "code": "ก558"
    },
    {
        "product_id": "77860977",
        "code": "ก557"
    },
    {
        "product_id": "77860761",
        "code": "ก556"
    },
    {
        "product_id": "77830214",
        "code": "ก555"
    },
    {
        "product_id": "77860975",
        "code": "ก555"
    },
    {
        "product_id": "77830211",
        "code": "ก554"
    },
    {
        "product_id": "77860756",
        "code": "ก554"
    },
    {
        "product_id": "77830210",
        "code": "ก553"
    },
    {
        "product_id": "77860750",
        "code": "ก553"
    },
    {
        "product_id": "77830209",
        "code": "ก552"
    },
    {
        "product_id": "77830207",
        "code": "ก551"
    },
    {
        "product_id": "77830205",
        "code": "ก550"
    },
    {
        "product_id": "77830204",
        "code": "ก549"
    },
    {
        "product_id": "77830203",
        "code": "ก548"
    },
    {
        "product_id": "77830202",
        "code": "ก547"
    },
    {
        "product_id": "77830201",
        "code": "ก546"
    },
    {
        "product_id": "77830189",
        "code": "ก545"
    },
    {
        "product_id": "77830188",
        "code": "ก544"
    },
    {
        "product_id": "77830183",
        "code": "ก543"
    },
    {
        "product_id": "77830180",
        "code": "ก542"
    },
    {
        "product_id": "77811430",
        "code": "ก541"
    },
    {
        "product_id": "77811428",
        "code": "ก540"
    },
    {
        "product_id": "77811424",
        "code": "ก539"
    },
    {
        "product_id": "77811423",
        "code": "ก538"
    },
    {
        "product_id": "77811421",
        "code": "ก537"
    },
    {
        "product_id": "77765417",
        "code": "ก536"
    },
    {
        "product_id": "77765315",
        "code": "ก535"
    },
    {
        "product_id": "77765308",
        "code": "ก534"
    },
    {
        "product_id": "77765303",
        "code": "ก533"
    },
    {
        "product_id": "77765290",
        "code": "ก532"
    },
    {
        "product_id": "77765281",
        "code": "ก530"
    },
    {
        "product_id": "77765271",
        "code": "ก529"
    },
    {
        "product_id": "77765270",
        "code": "ก528"
    },
    {
        "product_id": "77765263",
        "code": "ก527"
    },
    {
        "product_id": "77765260",
        "code": "ก526"
    },
    {
        "product_id": "77765257",
        "code": "ก525"
    },
    {
        "product_id": "77765267",
        "code": "ก524"
    },
    {
        "product_id": "77765255",
        "code": "ก523"
    },
    {
        "product_id": "77765252",
        "code": "ก522"
    },
    {
        "product_id": "77765251",
        "code": "ก521"
    },
    {
        "product_id": "77765250",
        "code": "ก520"
    },
    {
        "product_id": "77765245",
        "code": "ก519"
    },
    {
        "product_id": "77765243",
        "code": "ก518"
    },
    {
        "product_id": "77765165",
        "code": "ก516"
    },
    {
        "product_id": "77765160",
        "code": "ก515"
    },
    {
        "product_id": "77765156",
        "code": "ก514"
    },
    {
        "product_id": "77765150",
        "code": "ก513"
    },
    {
        "product_id": "77765129",
        "code": "ก512"
    },
    {
        "product_id": "77765124",
        "code": "ก511"
    },
    {
        "product_id": "77765121",
        "code": "ก510"
    },
    {
        "product_id": "77765118",
        "code": "ก509"
    },
    {
        "product_id": "77765116",
        "code": "ก508"
    },
    {
        "product_id": "77765183",
        "code": "ก507"
    },
    {
        "product_id": "77765168",
        "code": "ก506"
    },
    {
        "product_id": "77765175",
        "code": "ก505"
    },
    {
        "product_id": "77765146",
        "code": "ก504"
    },
    {
        "product_id": "77765075",
        "code": "ก503"
    },
    {
        "product_id": "77765050",
        "code": "ก502"
    },
    {
        "product_id": "77770461",
        "code": "ก501"
    },
    {
        "product_id": "77765022",
        "code": "ก500"
    },
    {
        "product_id": "77764984",
        "code": "ก491"
    },
    {
        "product_id": "77764429",
        "code": "ก490"
    },
    {
        "product_id": "76050094",
        "code": "ก49"
    },
    {
        "product_id": "77764370",
        "code": "ก489"
    },
    {
        "product_id": "77764365",
        "code": "ก488"
    },
    {
        "product_id": "77764361",
        "code": "ก487"
    },
    {
        "product_id": "77764343",
        "code": "ก486"
    },
    {
        "product_id": "77764307",
        "code": "ก484"
    },
    {
        "product_id": "77764277",
        "code": "ก482"
    },
    {
        "product_id": "77764228",
        "code": "ก481"
    },
    {
        "product_id": "77764251",
        "code": "ก480"
    },
    {
        "product_id": "77764214",
        "code": "ก479"
    },
    {
        "product_id": "77764076",
        "code": "ก478"
    },
    {
        "product_id": "77764213",
        "code": "ก477"
    },
    {
        "product_id": "77764071",
        "code": "ก476"
    },
    {
        "product_id": "77764079",
        "code": "ก475"
    },
    {
        "product_id": "77764069",
        "code": "ก474"
    },
    {
        "product_id": "77764067",
        "code": "ก473"
    },
    {
        "product_id": "77764063",
        "code": "ก472"
    },
    {
        "product_id": "77764061",
        "code": "ก471"
    },
    {
        "product_id": "77764057",
        "code": "ก469"
    },
    {
        "product_id": "77764052",
        "code": "ก468"
    },
    {
        "product_id": "77734949",
        "code": "ก467"
    },
    {
        "product_id": "77734946",
        "code": "ก465"
    },
    {
        "product_id": "77734945",
        "code": "ก464"
    },
    {
        "product_id": "77734943",
        "code": "ก463"
    },
    {
        "product_id": "77734738",
        "code": "ก462"
    },
    {
        "product_id": "77734737",
        "code": "ก461"
    },
    {
        "product_id": "77734736",
        "code": "ก460"
    },
    {
        "product_id": "77734735",
        "code": "ก459"
    },
    {
        "product_id": "77734734",
        "code": "ก458"
    },
    {
        "product_id": "77734733",
        "code": "ก457"
    },
    {
        "product_id": "77734732",
        "code": "ก456"
    },
    {
        "product_id": "77734731",
        "code": "ก455"
    },
    {
        "product_id": "77734730",
        "code": "ก454"
    },
    {
        "product_id": "77734729",
        "code": "ก453"
    },
    {
        "product_id": "77734728",
        "code": "ก452"
    },
    {
        "product_id": "77734727",
        "code": "ก451"
    },
    {
        "product_id": "77734726",
        "code": "ก450"
    },
    {
        "product_id": "77875619",
        "code": "ก432"
    },
    {
        "product_id": "77875608",
        "code": "ก431"
    },
    {
        "product_id": "77875609",
        "code": "ก430"
    },
    {
        "product_id": "77875600",
        "code": "ก429"
    },
    {
        "product_id": "77875598",
        "code": "ก428"
    },
    {
        "product_id": "77875592",
        "code": "ก427"
    },
    {
        "product_id": "78018574",
        "code": "ก426"
    },
    {
        "product_id": "78020531",
        "code": "ก426"
    },
    {
        "product_id": "77875589",
        "code": "ก425"
    },
    {
        "product_id": "77875612",
        "code": "ก424"
    },
    {
        "product_id": "77875593",
        "code": "ก423"
    },
    {
        "product_id": "77875585",
        "code": "ก422"
    },
    {
        "product_id": "77875583",
        "code": "ก421"
    },
    {
        "product_id": "77875581",
        "code": "ก420"
    },
    {
        "product_id": "77875580",
        "code": "ก418"
    },
    {
        "product_id": "77875575",
        "code": "ก417"
    },
    {
        "product_id": "77875573",
        "code": "ก416"
    },
    {
        "product_id": "77875571",
        "code": "ก415"
    },
    {
        "product_id": "77875569",
        "code": "ก413"
    },
    {
        "product_id": "77712698",
        "code": "ก410"
    },
    {
        "product_id": "77712695",
        "code": "ก409"
    },
    {
        "product_id": "77712692",
        "code": "ก408"
    },
    {
        "product_id": "77712690",
        "code": "ก407"
    },
    {
        "product_id": "77712689",
        "code": "ก406"
    },
    {
        "product_id": "77712688",
        "code": "ก405"
    },
    {
        "product_id": "77712685",
        "code": "ก404"
    },
    {
        "product_id": "77712684",
        "code": "ก403"
    },
    {
        "product_id": "77712682",
        "code": "ก402"
    },
    {
        "product_id": "77712516",
        "code": "ก401"
    },
    {
        "product_id": "77712490",
        "code": "ก400"
    },
    {
        "product_id": "77711921",
        "code": "ก399"
    },
    {
        "product_id": "77711909",
        "code": "ก398"
    },
    {
        "product_id": "77711907",
        "code": "ก397"
    },
    {
        "product_id": "77711906",
        "code": "ก396"
    },
    {
        "product_id": "77711904",
        "code": "ก395"
    },
    {
        "product_id": "77711903",
        "code": "ก394"
    },
    {
        "product_id": "77711900",
        "code": "ก392"
    },
    {
        "product_id": "77711895",
        "code": "ก391"
    },
    {
        "product_id": "77711894",
        "code": "ก390"
    },
    {
        "product_id": "77711891",
        "code": "ก389"
    },
    {
        "product_id": "77711885",
        "code": "ก388"
    },
    {
        "product_id": "77711745",
        "code": "ก387"
    },
    {
        "product_id": "77711726",
        "code": "ก386"
    },
    {
        "product_id": "77711713",
        "code": "ก385"
    },
    {
        "product_id": "77711709",
        "code": "ก384"
    },
    {
        "product_id": "77711708",
        "code": "ก383"
    },
    {
        "product_id": "77711706",
        "code": "ก382"
    },
    {
        "product_id": "77711703",
        "code": "ก381"
    },
    {
        "product_id": "77708526",
        "code": "ก380"
    },
    {
        "product_id": "77708525",
        "code": "ก379"
    },
    {
        "product_id": "77708524",
        "code": "ก378"
    },
    {
        "product_id": "77708523",
        "code": "ก377"
    },
    {
        "product_id": "77708522",
        "code": "ก375"
    },
    {
        "product_id": "77708520",
        "code": "ก374"
    },
    {
        "product_id": "77708519",
        "code": "ก373"
    },
    {
        "product_id": "77708518",
        "code": "ก372"
    },
    {
        "product_id": "77708517",
        "code": "ก371"
    },
    {
        "product_id": "77708514",
        "code": "ก370"
    },
    {
        "product_id": "77708513",
        "code": "ก369"
    },
    {
        "product_id": "77708508",
        "code": "ก368"
    },
    {
        "product_id": "77708507",
        "code": "ก367"
    },
    {
        "product_id": "77708505",
        "code": "ก366"
    },
    {
        "product_id": "77708504",
        "code": "ก365"
    },
    {
        "product_id": "77708503",
        "code": "ก364"
    },
    {
        "product_id": "77708502",
        "code": "ก363"
    },
    {
        "product_id": "77708500",
        "code": "ก362"
    },
    {
        "product_id": "77708499",
        "code": "ก361"
    },
    {
        "product_id": "77708498",
        "code": "ก360"
    },
    {
        "product_id": "76723486",
        "code": "ก358"
    },
    {
        "product_id": "76723728",
        "code": "ก358"
    },
    {
        "product_id": "76723664",
        "code": "ก356"
    },
    {
        "product_id": "76724189",
        "code": "ก355"
    },
    {
        "product_id": "76723659",
        "code": "ก354"
    },
    {
        "product_id": "76724163",
        "code": "ก353"
    },
    {
        "product_id": "76723616",
        "code": "ก352"
    },
    {
        "product_id": "76723559",
        "code": "ก351"
    },
    {
        "product_id": "76723497",
        "code": "ก349"
    },
    {
        "product_id": "76712952",
        "code": "ก348"
    },
    {
        "product_id": "76712906",
        "code": "ก347"
    },
    {
        "product_id": "76712896",
        "code": "ก346"
    },
    {
        "product_id": "76712892",
        "code": "ก345"
    },
    {
        "product_id": "76712888",
        "code": "ก344"
    },
    {
        "product_id": "76710620",
        "code": "ก343"
    },
    {
        "product_id": "76710597",
        "code": "ก342"
    },
    {
        "product_id": "76710544",
        "code": "ก341"
    },
    {
        "product_id": "76710289",
        "code": "ก340"
    },
    {
        "product_id": "76710247",
        "code": "ก339"
    },
    {
        "product_id": "76710235",
        "code": "ก338"
    },
    {
        "product_id": "76709764",
        "code": "ก337"
    },
    {
        "product_id": "76709746",
        "code": "ก336"
    },
    {
        "product_id": "76709726",
        "code": "ก335"
    },
    {
        "product_id": "76709719",
        "code": "ก334"
    },
    {
        "product_id": "76709698",
        "code": "ก333"
    },
    {
        "product_id": "76709658",
        "code": "ก332"
    },
    {
        "product_id": "76709593",
        "code": "ก331"
    },
    {
        "product_id": "76709578",
        "code": "ก330"
    },
    {
        "product_id": "76708518",
        "code": "ก329"
    },
    {
        "product_id": "76708451",
        "code": "ก328"
    },
    {
        "product_id": "76708400",
        "code": "ก327"
    },
    {
        "product_id": "76708290",
        "code": "ก326"
    },
    {
        "product_id": "76708269",
        "code": "ก325"
    },
    {
        "product_id": "76708233",
        "code": "ก324"
    },
    {
        "product_id": "76708232",
        "code": "ก323"
    },
    {
        "product_id": "76708206",
        "code": "ก322"
    },
    {
        "product_id": "77891803",
        "code": "ก322"
    },
    {
        "product_id": "76708194",
        "code": "ก321"
    },
    {
        "product_id": "76708189",
        "code": "ก320"
    },
    {
        "product_id": "76708185",
        "code": "ก319"
    },
    {
        "product_id": "76699976",
        "code": "ก318"
    },
    {
        "product_id": "76699970",
        "code": "ก317"
    },
    {
        "product_id": "76699967",
        "code": "ก316"
    },
    {
        "product_id": "76699965",
        "code": "ก315"
    },
    {
        "product_id": "76699962",
        "code": "ก314"
    },
    {
        "product_id": "76699959",
        "code": "ก313"
    },
    {
        "product_id": "76699953",
        "code": "ก312"
    },
    {
        "product_id": "76699947",
        "code": "ก311"
    },
    {
        "product_id": "76699944",
        "code": "ก310"
    },
    {
        "product_id": "76699880",
        "code": "ก309"
    },
    {
        "product_id": "76699876",
        "code": "ก308"
    },
    {
        "product_id": "76699863",
        "code": "ก307"
    },
    {
        "product_id": "76699859",
        "code": "ก306"
    },
    {
        "product_id": "76699854",
        "code": "ก305"
    },
    {
        "product_id": "76699846",
        "code": "ก304"
    },
    {
        "product_id": "76699833",
        "code": "ก303"
    },
    {
        "product_id": "76699827",
        "code": "ก302"
    },
    {
        "product_id": "76699821",
        "code": "ก301"
    },
    {
        "product_id": "76699812",
        "code": "ก300"
    },
    {
        "product_id": "76390245",
        "code": "ก282"
    },
    {
        "product_id": "76390234",
        "code": "ก281"
    },
    {
        "product_id": "76390231",
        "code": "ก280"
    },
    {
        "product_id": "76390186",
        "code": "ก279"
    },
    {
        "product_id": "76390175",
        "code": "ก278"
    },
    {
        "product_id": "76390145",
        "code": "ก277"
    },
    {
        "product_id": "76390091",
        "code": "ก276"
    },
    {
        "product_id": "76390075",
        "code": "ก275"
    },
    {
        "product_id": "76390050",
        "code": "ก274"
    },
    {
        "product_id": "76389983",
        "code": "ก273"
    },
    {
        "product_id": "76389972",
        "code": "ก272"
    },
    {
        "product_id": "76389894",
        "code": "ก270"
    },
    {
        "product_id": "76389872",
        "code": "ก268"
    },
    {
        "product_id": "76389884",
        "code": "ก267"
    },
    {
        "product_id": "76389854",
        "code": "ก266"
    },
    {
        "product_id": "76389848",
        "code": "ก265"
    },
    {
        "product_id": "76389853",
        "code": "ก264"
    },
    {
        "product_id": "76389835",
        "code": "ก262"
    },
    {
        "product_id": "76389832",
        "code": "ก261"
    },
    {
        "product_id": "76389827",
        "code": "ก260"
    },
    {
        "product_id": "76389825",
        "code": "ก259"
    },
    {
        "product_id": "76390218",
        "code": "ก257"
    },
    {
        "product_id": "76389871",
        "code": "ก256"
    },
    {
        "product_id": "76389865",
        "code": "ก255"
    },
    {
        "product_id": "76389864",
        "code": "ก254"
    },
    {
        "product_id": "76389883",
        "code": "ก254"
    },
    {
        "product_id": "76389877",
        "code": "ก253"
    },
    {
        "product_id": "76389876",
        "code": "ก252"
    },
    {
        "product_id": "76387877",
        "code": "ก251"
    },
    {
        "product_id": "76387834",
        "code": "ก250"
    },
    {
        "product_id": "76387831",
        "code": "ก249"
    },
    {
        "product_id": "76387800",
        "code": "ก248"
    },
    {
        "product_id": "76387811",
        "code": "ก247"
    },
    {
        "product_id": "76387813",
        "code": "ก246"
    },
    {
        "product_id": "76387814",
        "code": "ก245"
    },
    {
        "product_id": "76387827",
        "code": "ก244"
    },
    {
        "product_id": "76387808",
        "code": "ก243"
    },
    {
        "product_id": "76387795",
        "code": "ก242"
    },
    {
        "product_id": "76387799",
        "code": "ก241"
    },
    {
        "product_id": "76387759",
        "code": "ก240"
    },
    {
        "product_id": "76387753",
        "code": "ก239"
    },
    {
        "product_id": "76387746",
        "code": "ก238"
    },
    {
        "product_id": "76387740",
        "code": "ก237"
    },
    {
        "product_id": "76340751",
        "code": "ก236"
    },
    {
        "product_id": "76340644",
        "code": "ก235"
    },
    {
        "product_id": "76340649",
        "code": "ก234"
    },
    {
        "product_id": "76340552",
        "code": "ก233"
    },
    {
        "product_id": "76339421",
        "code": "ก232"
    },
    {
        "product_id": "76338570",
        "code": "ก231"
    },
    {
        "product_id": "76340406",
        "code": "ก230"
    },
    {
        "product_id": "76340394",
        "code": "ก228"
    },
    {
        "product_id": "76340389",
        "code": "ก226"
    },
    {
        "product_id": "76340385",
        "code": "ก225"
    },
    {
        "product_id": "76340381",
        "code": "ก224"
    },
    {
        "product_id": "76340372",
        "code": "ก223"
    },
    {
        "product_id": "76340367",
        "code": "ก222"
    },
    {
        "product_id": "76642668",
        "code": "ก221"
    },
    {
        "product_id": "76337929",
        "code": "ก220"
    },
    {
        "product_id": "76337902",
        "code": "ก219"
    },
    {
        "product_id": "76337184",
        "code": "ก218"
    },
    {
        "product_id": "76337187",
        "code": "ก217"
    },
    {
        "product_id": "76337180",
        "code": "ก216"
    },
    {
        "product_id": "76337175",
        "code": "ก215"
    },
    {
        "product_id": "76452561",
        "code": "ก214"
    },
    {
        "product_id": "76337148",
        "code": "ก213"
    },
    {
        "product_id": "76337136",
        "code": "ก212"
    },
    {
        "product_id": "76337141",
        "code": "ก211"
    },
    {
        "product_id": "76337138",
        "code": "ก210"
    },
    {
        "product_id": "76337140",
        "code": "ก209"
    },
    {
        "product_id": "76337149",
        "code": "ก208"
    },
    {
        "product_id": "76337152",
        "code": "ก207"
    },
    {
        "product_id": "76337155",
        "code": "ก206"
    },
    {
        "product_id": "76337133",
        "code": "ก205"
    },
    {
        "product_id": "76337131",
        "code": "ก204"
    },
    {
        "product_id": "76337132",
        "code": "ก203"
    },
    {
        "product_id": "76343051",
        "code": "ก202"
    },
    {
        "product_id": "76343030",
        "code": "ก201"
    },
    {
        "product_id": "76336962",
        "code": "ก200"
    },
    {
        "product_id": "76287373",
        "code": "ก174"
    },
    {
        "product_id": "76286951",
        "code": "ก171"
    },
    {
        "product_id": "76286940",
        "code": "ก170"
    },
    {
        "product_id": "76287627",
        "code": "ก161"
    },
    {
        "product_id": "76287396",
        "code": "ก160"
    },
    {
        "product_id": "76287390",
        "code": "ก159"
    },
    {
        "product_id": "76287286",
        "code": "ก158"
    },
    {
        "product_id": "76286959",
        "code": "ก157"
    },
    {
        "product_id": "76286956",
        "code": "ก156"
    },
    {
        "product_id": "76287093",
        "code": "ก155"
    },
    {
        "product_id": "76288841",
        "code": "ก154"
    },
    {
        "product_id": "76286920",
        "code": "ก153"
    },
    {
        "product_id": "76272683",
        "code": "ก152"
    },
    {
        "product_id": "76274389",
        "code": "ก151"
    },
    {
        "product_id": "76272677",
        "code": "ก150"
    },
    {
        "product_id": "76272648",
        "code": "ก149"
    },
    {
        "product_id": "76272647",
        "code": "ก148"
    },
    {
        "product_id": "76272642",
        "code": "ก147"
    },
    {
        "product_id": "76272631",
        "code": "ก146"
    },
    {
        "product_id": "76272630",
        "code": "ก145"
    },
    {
        "product_id": "76272624",
        "code": "ก144"
    },
    {
        "product_id": "76272378",
        "code": "ก143"
    },
    {
        "product_id": "76272389",
        "code": "ก142"
    },
    {
        "product_id": "76272433",
        "code": "ก139"
    },
    {
        "product_id": "76272455",
        "code": "ก138"
    },
    {
        "product_id": "76272420",
        "code": "ก137"
    },
    {
        "product_id": "76272447",
        "code": "ก136"
    },
    {
        "product_id": "76270180",
        "code": "ก134"
    },
    {
        "product_id": "76270178",
        "code": "ก132"
    },
    {
        "product_id": "76270176",
        "code": "ก131"
    },
    {
        "product_id": "76270174",
        "code": "ก130"
    },
    {
        "product_id": "76270173",
        "code": "ก129"
    },
    {
        "product_id": "76268888",
        "code": "ก128"
    },
    {
        "product_id": "76268877",
        "code": "ก127"
    },
    {
        "product_id": "76268880",
        "code": "ก126"
    },
    {
        "product_id": "76268872",
        "code": "ก125"
    },
    {
        "product_id": "76268867",
        "code": "ก124"
    },
    {
        "product_id": "76268864",
        "code": "ก123"
    },
    {
        "product_id": "76268862",
        "code": "ก122"
    },
    {
        "product_id": "76268860",
        "code": "ก121"
    },
    {
        "product_id": "76268856",
        "code": "ก120"
    },
    {
        "product_id": "76268847",
        "code": "ก119"
    },
    {
        "product_id": "76268846",
        "code": "ก118"
    },
    {
        "product_id": "76268844",
        "code": "ก117"
    },
    {
        "product_id": "76268842",
        "code": "ก116"
    },
    {
        "product_id": "76268837",
        "code": "ก115"
    },
    {
        "product_id": "76268830",
        "code": "ก114"
    },
    {
        "product_id": "76268827",
        "code": "ก113"
    },
    {
        "product_id": "76268823",
        "code": "ก112"
    },
    {
        "product_id": "76268818",
        "code": "ก111"
    },
    {
        "product_id": "76268821",
        "code": "ก110"
    },
    {
        "product_id": "76268820",
        "code": "ก109"
    },
    {
        "product_id": "76268815",
        "code": "ก108"
    },
    {
        "product_id": "76268809",
        "code": "ก107"
    },
    {
        "product_id": "76268804",
        "code": "ก106"
    }
]